wodoo/__init__.py
wodoo/click_config.py
wodoo/click_global_commands.py
wodoo/consts.py
wodoo/defaults
wodoo/init_functions.py
wodoo/lib_backup.py
wodoo/lib_clickhelpers.py
wodoo/lib_composer.py
wodoo/lib_control.py
wodoo/lib_control_native.py
wodoo/lib_control_with_docker.py
wodoo/lib_db.py
wodoo/lib_db_snapshots.py
wodoo/lib_db_snapshots_docker_btrfs.py
wodoo/lib_db_snapshots_plain_postgres.py
wodoo/lib_docker_registry.py
wodoo/lib_lang.py
wodoo/lib_module.py
wodoo/lib_setup.py
wodoo/lib_src.py
wodoo/lib_turnintodev.py
wodoo/lib_venv.py
wodoo/module_tools.py
wodoo/myconfigparser.py
wodoo/odoo_config.py
wodoo/odoo_parser.py
wodoo/program_settings.py
wodoo/pudb.cfg
wodoo/requirements.txt
wodoo/robo_helpers.py
wodoo/settings.py
wodoo/tools.py
wodoo/config/cicd_network_for_project.yml
wodoo/config/default_network
wodoo/config/template_onlyloop.yml
wodoo/config/template_withports.yml
wodoo/customs_template/11.0/MANIFEST
wodoo/customs_template/13.0/MANIFEST
wodoo/customs_template/15.0/MANIFEST
wodoo/customs_template/15.0/gimera.yml
wodoo/customs_template/9.0/install
wodoo/customs_template/9.0/readme.txt
wodoo/extra_install/asterisk_customs/connector_mqtt_asterisk/Dockerfile
wodoo/extra_install/asterisk_customs/connector_mqtt_asterisk/README.txt
wodoo/extra_install/asterisk_customs/connector_mqtt_asterisk/debug.sh
wodoo/extra_install/asterisk_customs/connector_mqtt_asterisk/docker-compose.yml
wodoo/extra_install/asterisk_customs/connector_mqtt_asterisk/entrypoint.sh
wodoo/extra_install/asterisk_customs/connector_mqtt_asterisk/interactive.sh
wodoo/extra_install/asterisk_customs/connector_mqtt_asterisk/requirements.txt
wodoo/extra_install/asterisk_customs/connector_mqtt_asterisk/ssh/config
wodoo/extra_install/asterisk_customs/connector_mqtt_asterisk/ssh/id_rsa
wodoo/extra_install/asterisk_customs/connector_mqtt_asterisk/ssh/id_rsa.pub
wodoo/extra_install/asterisk_customs/docker-freepbx/ANPASSUNGEN.txt
wodoo/extra_install/asterisk_customs/docker-freepbx/Dockerfile
wodoo-0.2.11.dist-info/LICENSE
wodoo-0.2.11.dist-info/METADATA
wodoo-0.2.11.dist-info/WHEEL
wodoo-0.2.11.dist-info/entry_points.txt
wodoo-0.2.11.dist-info/top_level.txt
wodoo-0.2.11.dist-info/RECORD
