Metadata-Version: 2.1
Name: wodoo
Version: 0.2.11
Summary: 'Odoo Framework'
Home-page: https://github.com/marcwimmer/wodoo
Author: 'Marc-Christian Wimmer'
License: 'MIT'
Platform: UNKNOWN
Classifier: License :: OSI Approved :: MIT License
Classifier: Programming Language :: Python
Classifier: Programming Language :: Python :: 3
Classifier: Programming Language :: Python :: 3.6
Classifier: Programming Language :: Python :: Implementation :: CPython
Classifier: Programming Language :: Python :: Implementation :: PyPy
License-File: LICENSE
Requires-Dist: pyyaml
Requires-Dist: arrow (>=0.14.6)
Requires-Dist: Click (>=8.0.1)
Requires-Dist: click-default-group (>=1.2.1)
Requires-Dist: pathlib (>=1.0.1)
Requires-Dist: inquirer (>=2.6.3)
Requires-Dist: retrying (>=1.3.3)
Requires-Dist: humanize (>=0.5.1)
Requires-Dist: passlib (>=1.7.1)
Requires-Dist: tabulate (>=0.8.3)
Requires-Dist: psycopg2-binary (>=2.8.3)
Requires-Dist: requests (>=2.20.1)
Requires-Dist: lxml (>=4.4.1)
Requires-Dist: psutil (>=5.6.3)
Requires-Dist: GitPython (>=3.1.11)
Requires-Dist: docker-compose (==1.27.3)
Requires-Dist: iscompatible
Requires-Dist: buttervolume (>=3.7)
Requires-Dist: pudb
Requires-Dist: gimera
Requires-Dist: shellingham
